changelog/.gitempty
dkist_spectral_lines/__init__.py
dkist_spectral_lines/_version.py
dkist_spectral_lines/lines.py
dkist_spectral_lines/models.py
dkist_spectral_lines/search.py
dkist_spectral_lines/tests/__init__.py
dkist_spectral_lines/tests/test_lines.py
dkist_spectral_lines/tests/test_models.py
dkist_spectral_lines/tests/test_search.py
docs/Makefile
docs/changelog.rst
docs/conf.py
docs/index.rst
docs/make.bat
licenses/LICENSE.rst
dkist_spectral_lines-3.0.0.dist-info/LICENSE
dkist_spectral_lines-3.0.0.dist-info/METADATA
dkist_spectral_lines-3.0.0.dist-info/WHEEL
dkist_spectral_lines-3.0.0.dist-info/top_level.txt
dkist_spectral_lines-3.0.0.dist-info/RECORD
