Metadata-Version: 2.1
Name: dkist-spectral-lines
Version: 3.0.0
Summary: Spectral line metadata for the DKIST suite of instruments.
Author-email: NSO / AURA <dkistdc@nso.edu>
License: MIT
Project-URL: repository, https://docs.dkist.nso.edu/projects/spectral-lines
Project-URL: documentation, https://docs.dkist.nso.edu/projects/spectral-lines
Classifier: License :: OSI Approved :: MIT License
Classifier: Programming Language :: Python :: 3
Classifier: Programming Language :: Python :: 3.11
Requires-Python: >=3.11
License-File: LICENSE
Requires-Dist: pydantic >2.0
Requires-Dist: astropy >5.1.0
Provides-Extra: docs
Requires-Dist: sphinx ; extra == 'docs'
Requires-Dist: sphinx-astropy ; extra == 'docs'
Requires-Dist: sphinx-changelog ; extra == 'docs'
Requires-Dist: sphinx-autoapi ; extra == 'docs'
Requires-Dist: pytest ; extra == 'docs'
Requires-Dist: towncrier ; extra == 'docs'
Requires-Dist: dkist-sphinx-theme ; extra == 'docs'
Provides-Extra: test
Requires-Dist: tox >=4 ; extra == 'test'
Requires-Dist: pytest ; extra == 'test'
Requires-Dist: pytest-cov ; extra == 'test'
Requires-Dist: pytest-mock ; extra == 'test'
Requires-Dist: towncrier ; extra == 'test'
Requires-Dist: Pygments ; extra == 'test'
Requires-Dist: PyPDF4 ; extra == 'test'
